{
    "font": {
        "title_size": 16,
        "axis_tick_size": 11,
        "legend_size": 10,
        "stat_card_value_rem": 1.6,
        "stat_card_label_rem": 0.82
    },
    "chart": {
        "height": 400,
        "line_width_raw": 1.5,
        "line_width_ma5": 2.5,
        "raw_alpha": 0.35,
        "band_alpha_outer": 0.08,
        "band_alpha_inner": 0.18,
        "show_bands": false,
        "show_median": true,
        "show_p5_p95": true,
        "show_iqr_outlier": true
    },
    "palette": {
        "primary": "#DC2626",
        "positive": "#FB923C",
        "negative": "#4ADE80",
        "p5p95_color": "#3D5A73",
        "sma_colors": [
            "#F59E0B",
            "#06B6D4",
            "#F97316"
        ],
        "median_color": "#B8C4CE",
        "iqr_outlier_color": "#F43F5E",
        "p25p75_color": "#7B8FA2",
        "bull_area": "rgba(251,146,60,0.25)",
        "bear_area": "rgba(74,222,128,0.22)",
        "bull_line": "#DC2626",
        "bear_line": "#15803D"
    },
    "table": {
        "show_all_columns": false,
        "height": 480
    },
    "lookback": 1000
}
